Metadata-Version: 2.1
Name: zenpy
Version: 2.0.27
Summary: Python wrapper for the Zendesk API
Project-URL: Homepage, https://github.com/facetoe/zenpy
Project-URL: Bug Tracker, https://github.com/faceto/zenpy/issues
Author-email: William Coe <facetoe@facetoe.com.au>
License-File: LICENSE
Classifier: License :: OSI Approved :: MIT License
Classifier: Operating System :: OS Independent
Classifier: Programming Language :: Python :: 3
Requires-Python: >=2.7
